confite/__init__.py
confite/output_formatter.py
confite-1.0.5.dist-info/LICENSE
confite-1.0.5.dist-info/METADATA
confite-1.0.5.dist-info/WHEEL
confite-1.0.5.dist-info/top_level.txt
confite-1.0.5.dist-info/RECORD
