Metadata-Version: 2.1
Name: confite
Version: 1.0.5
Summary: A simple and tiny class to easily manage configurations
Home-page: UNKNOWN
Author: HackyDojo
Author-email: info@subvertic.com
License: UNKNOWN
Platform: UNKNOWN
Classifier: Development Status :: 1 - Planning
Classifier: Intended Audience :: Developers
Classifier: License :: OSI Approved :: MIT License
Classifier: Operating System :: POSIX :: Linux
Classifier: Programming Language :: Python :: 3.4
Classifier: Programming Language :: Python :: 3.5
License-File: LICENSE
